README.md
setup.cfg
setup.py
triple_t/Board.py
triple_t/Play.py
triple_t/Player.py
triple_t/__init__.py
triple_t.egg-info/PKG-INFO
triple_t.egg-info/SOURCES.txt
triple_t.egg-info/dependency_links.txt
triple_t.egg-info/not-zip-safe
triple_t.egg-info/top_level.txt