Metadata-Version: 1.0
Name: triple-t
Version: 0.1
Summary: Tic Tac Toe game
Home-page: UNKNOWN
Author: Amro Ghoneim
Author-email: amroghoneim@aucegypt.edu
License: UNKNOWN
Platform: UNKNOWN
